frigate/__init__.py
frigate/__main__.py
frigate/_version.py
frigate/cli.py
frigate/gen.py
frigate/pre_commit_hook.py
frigate/utils.py
frigate/sphinx/__init__.py
frigate/sphinx/ext.py
frigate/templates/base.jinja2
frigate/templates/html.jinja2
frigate/templates/markdown.jinja2
frigate/templates/rst.jinja2
frigate-0.7.0.dist-info/LICENSE
frigate-0.7.0.dist-info/METADATA
frigate-0.7.0.dist-info/WHEEL
frigate-0.7.0.dist-info/entry_points.txt
frigate-0.7.0.dist-info/top_level.txt
frigate-0.7.0.dist-info/RECORD
