Metadata-Version: 2.1
Name: frigate
Version: 0.7.0
Summary: A tool for autogenerating helm documentation.
Home-page: 
Download-URL: 
Author: Jacob Tomlinson
Author-email: jtomlinson@nvidia.com
License: Apache License 2.0
Platform: any
License-File: LICENSE
Requires-Dist: click
Requires-Dist: docutils
Requires-Dist: jinja2
Requires-Dist: ruamel.yaml
